PythonZuijiaShijianZhinan/README.md
PythonZuijiaShijianZhinan/__init__.py
PythonZuijiaShijianZhinan/__main__.py
PythonZuijiaShijianZhinan/file.epub
PythonZuijiaShijianZhinan/index.html
PythonZuijiaShijianZhinan/css/__init__.py
PythonZuijiaShijianZhinan/css/annotations.css
PythonZuijiaShijianZhinan/css/main.css
PythonZuijiaShijianZhinan/css/normalize.css
PythonZuijiaShijianZhinan/css/popup.css
PythonZuijiaShijianZhinan/font/__init__.py
PythonZuijiaShijianZhinan/font/fontello.eot
PythonZuijiaShijianZhinan/font/fontello.svg
PythonZuijiaShijianZhinan/font/fontello.ttf
PythonZuijiaShijianZhinan/font/fontello.woff
PythonZuijiaShijianZhinan/img/__init__.py
PythonZuijiaShijianZhinan/img/annotator-glyph-sprite.png
PythonZuijiaShijianZhinan/img/annotator-icon-sprite.png
PythonZuijiaShijianZhinan/img/apple-touch-icon.png
PythonZuijiaShijianZhinan/img/cancelfullscreen.png
PythonZuijiaShijianZhinan/img/close.png
PythonZuijiaShijianZhinan/img/fullscreen.png
PythonZuijiaShijianZhinan/img/loader.gif
PythonZuijiaShijianZhinan/img/menu-icon.png
PythonZuijiaShijianZhinan/img/save.png
PythonZuijiaShijianZhinan/img/saved.png
PythonZuijiaShijianZhinan/img/settings-s.png
PythonZuijiaShijianZhinan/img/settings.png
PythonZuijiaShijianZhinan/img/star.png
PythonZuijiaShijianZhinan/js/__init__.py
PythonZuijiaShijianZhinan/js/epub.js
PythonZuijiaShijianZhinan/js/epub.min.js
PythonZuijiaShijianZhinan/js/epub.min.map
PythonZuijiaShijianZhinan/js/hooks.min.js
PythonZuijiaShijianZhinan/js/hooks.min.map
PythonZuijiaShijianZhinan/js/reader.js
PythonZuijiaShijianZhinan/js/reader.js.map
PythonZuijiaShijianZhinan/js/reader.min.js
PythonZuijiaShijianZhinan/js/reader.min.map
PythonZuijiaShijianZhinan/js/hooks/__init__.py
PythonZuijiaShijianZhinan/js/hooks/extensions/__init__.py
PythonZuijiaShijianZhinan/js/hooks/extensions/highlight.js
PythonZuijiaShijianZhinan/js/libs/__init__.py
PythonZuijiaShijianZhinan/js/libs/jquery.min.js
PythonZuijiaShijianZhinan/js/libs/localforage.min.js
python_zuijia_shijian_zhinan-2024.3.2.0.dist-info/METADATA
python_zuijia_shijian_zhinan-2024.3.2.0.dist-info/WHEEL
python_zuijia_shijian_zhinan-2024.3.2.0.dist-info/entry_points.txt
python_zuijia_shijian_zhinan-2024.3.2.0.dist-info/top_level.txt
python_zuijia_shijian_zhinan-2024.3.2.0.dist-info/RECORD
